{
  "stats": {
    "tinkersarchery:arrowhead": {
      "count": 31,
      "miningSpeed": 6.0,
      "harvestLevel": 2,
      "attack": 3.0,
      "weight": 0.65,
      "stability": 1.35,
      "accuracy": 1.1
    },
    "tinkersarchery:bow": {
      "durability": 530,
      "elasticity": 2.5,
      "drawSpeed": 1.35
    },
    "tinkersarchery:bowguide": {},
    "tinkersarchery:arrow_shaft": {
      "count": 0.85,
      "miningSpeed": 1.05,
      "attackSpeed": 1.2,
      "attackDamage": 1.0,
      "weight": 0.65,
      "stability": 1.35,
      "accuracy": 1.0
    }
  }
}